arcana/__init__.py
arcana/logger/__init__.py
arcana/logger/logger.py
arcana/losses/__init__.py
arcana/losses/loss.py
arcana/losses/loss_trace.py
arcana/models/__init__.py
arcana/models/decoders/__init__.py
arcana/models/decoders/additive_decoder.py
arcana/models/decoders/base_decoder.py
arcana/models/decoders/multihead_decoder.py
arcana/models/encoders/__init__.py
arcana/models/encoders/additive_encoder.py
arcana/models/encoders/base_encoder.py
arcana/models/encoders/multihead_encoder.py
arcana/models/sequence_to_sequence/__init__.py
arcana/models/sequence_to_sequence/seq2seq_factory.py
arcana/models/sequence_to_sequence/sequence_to_sequence.py
arcana/plots/__init__.py
arcana/plots/analysis_plot_utils.py
arcana/plots/plot_utils.py
arcana/plots/plots.py
arcana/prediction/__init__.py
arcana/prediction/quantile_prediction.py
arcana/procedures/__init__.py
arcana/procedures/config_handler.py
arcana/procedures/finetuning.py
arcana/procedures/predicting.py
arcana/procedures/training.py
arcana/procedures/tuning.py
arcana/processing/__init__.py
arcana/processing/data_processing.py
arcana/regularizations/__init__.py
arcana/regularizations/optimizer_scheduler.py
arcana/regularizations/stopping_criteria.py
arcana/regularizations/teacher_forcing.py
arcana/training/__init__.py
arcana/training/train_model.py
arcana/utils/__init__.py
arcana/utils/utils.py
arcana_batt-1.0.1.dist-info/AUTHORS.rst
arcana_batt-1.0.1.dist-info/License.txt
arcana_batt-1.0.1.dist-info/METADATA
arcana_batt-1.0.1.dist-info/WHEEL
arcana_batt-1.0.1.dist-info/top_level.txt
arcana_batt-1.0.1.dist-info/RECORD
